octavia_lib/__init__.py
octavia_lib/i18n.py
octavia_lib/version.py
octavia_lib/api/__init__.py
octavia_lib/api/drivers/__init__.py
octavia_lib/api/drivers/data_models.py
octavia_lib/api/drivers/driver_lib.py
octavia_lib/api/drivers/exceptions.py
octavia_lib/api/drivers/provider_base.py
octavia_lib/common/__init__.py
octavia_lib/common/constants.py
octavia_lib/hacking/__init__.py
octavia_lib/hacking/checks.py
octavia_lib/tests/__init__.py
octavia_lib/tests/unit/__init__.py
octavia_lib/tests/unit/base.py
octavia_lib/tests/unit/api/__init__.py
octavia_lib/tests/unit/api/drivers/__init__.py
octavia_lib/tests/unit/api/drivers/test_data_models.py
octavia_lib/tests/unit/api/drivers/test_driver_lib.py
octavia_lib/tests/unit/api/drivers/test_exceptions.py
octavia_lib/tests/unit/api/drivers/test_provider_base.py
octavia_lib/tests/unit/hacking/__init__.py
octavia_lib/tests/unit/hacking/test_checks.py
octavia_lib-3.10.0.dist-info/AUTHORS
octavia_lib-3.10.0.dist-info/LICENSE
octavia_lib-3.10.0.dist-info/METADATA
octavia_lib-3.10.0.dist-info/WHEEL
octavia_lib-3.10.0.dist-info/pbr.json
octavia_lib-3.10.0.dist-info/top_level.txt
octavia_lib-3.10.0.dist-info/RECORD
