Metadata-Version: 2.1
Name: octavia-lib
Version: 3.10.0
Summary: A library to support Octavia provider drivers.
Home-page: https://docs.openstack.org/octavia-lib/latest/
Author: OpenStack
Author-email: openstack-discuss@lists.openstack.org
License: Apache License, Version 2.0
Classifier: Development Status :: 5 - Production/Stable
Classifier: Environment :: OpenStack
Classifier: Intended Audience :: Developers
Classifier: Intended Audience :: Information Technology
Classifier: Intended Audience :: System Administrators
Classifier: License :: OSI Approved :: Apache Software License
Classifier: Operating System :: POSIX :: Linux
Classifier: Programming Language :: Python
Classifier: Programming Language :: Python :: 3
Classifier: Programming Language :: Python :: 3.10
Classifier: Programming Language :: Python :: 3.11
Classifier: Programming Language :: Python :: 3.12
Requires-Python: >=3.10
License-File: LICENSE
License-File: AUTHORS
Requires-Dist: oslo.i18n >=3.15.3
Requires-Dist: oslo.serialization >=2.28.1
Requires-Dist: pbr !=2.1.0,>=2.0.0
Requires-Dist: tenacity >=5.0.2
